[{"tour_id": 917214, "name": "Кубок мира 1982", "place": 4, "prise": 2125000}, {"tour_id": 917214, "name": "Кубок мира 1982", "place": 9, "prise": 66406}, {"tour_id": 917214, "name": "Кубок мира 1982", "place": 5, "prise": 1062500}, {"tour_id": 725339, "name": "Политика 1994", "place": 2, "prise": 4000000}, {"tour_id": 917214, "name": "Кубок мира 1982", "place": 0, "prise": 34000000}, {"tour_id": 917214, "name": "Кубок мира 1982", "place": 10, "prise": 33203}, {"tour_id": 917214, "name": "Кубок мира 1982", "place": 11, "prise": 16602}, {"tour_id": 917214, "name": "Кубок мира 1982", "place": 1, "prise": 17000000}, {"tour_id": 917214, "name": "Кубок мира 1982", "place": 3, "prise": 4250000}, {"tour_id": 725339, "name": "Политика 1994", "place": 1, "prise": 8000000}, {"tour_id": 917214, "name": "Кубок мира 1982", "place": 6, "prise": 531250}, {"tour_id": 917214, "name": "Кубок мира 1982", "place": 2, "prise": 8500000}, {"tour_id": 917214, "name": "Кубок мира 1982", "place": 7, "prise": 265625}, {"tour_id": 725339, "name": "Политика 1994", "place": 0, "prise": 16000000}, {"tour_id": 917214, "name": "Кубок мира 1982", "place": 8, "prise": 132812}]