<?xml version="1.0" encoding="utf-8"?>
<clothing-items>
 <clothing>
  <id>
   410106705
  </id>
  <name>
   PleinSport Umbrellas T-1069
  </name>
  <category>
   Umbrellas
  </category>
  <size>
   S
  </size>
  <color>
   Синий
  </color>
  <material>
   Полиэстер
  </material>
  <price>
   929587
  </price>
  <rating>
   2.17
  </rating>
  <reviews>
   191913
  </reviews>
  <new>
   -
  </new>
  <exclusive>
   no
  </exclusive>
 </clothing>
 <clothing>
  <id>
   785449071
  </id>
  <name>
   Nike Handbags N-4432
  </name>
  <category>
   Handbags
  </category>
  <size>
   M
  </size>
  <color>
   Оранжевый
  </color>
  <material>
   Шелк
  </material>
  <price>
   656075
  </price>
  <rating>
   4.23
  </rating>
  <reviews>
   645407
  </reviews>
  <new>
   -
  </new>
  <exclusive>
   no
  </exclusive>
  <sporty>
   yes
  </sporty>
 </clothing>
 <clothing>
  <id>
   961607239
  </id>
  <name>
   Vans Handbags I-8212
  </name>
  <category>
   Handbags
  </category>
  <size>
   XXL
  </size>
  <color>
   Фиолетовый
  </color>
  <material>
   Лен
  </material>
  <price>
   510767
  </price>
  <rating>
   1.01
  </rating>
  <reviews>
   818125
  </reviews>
  <exclusive>
   yes
  </exclusive>
 </clothing>
 <clothing>
  <id>
   207921893
  </id>
  <name>
   Under Armour Blouse V-5046
  </name>
  <category>
   Blouse
  </category>
  <size>
   XL
  </size>
  <color>
   Красный
  </color>
  <material>
   Лен
  </material>
  <price>
   923330
  </price>
  <rating>
   4.79
  </rating>
  <reviews>
   789308
  </reviews>
  <new>
   +
  </new>
 </clothing>
 <clothing>
  <id>
   224195285
  </id>
  <name>
   Vans Skirt R-2931
  </name>
  <category>
   Skirt
  </category>
  <size>
   M
  </size>
  <color>
   Желтый
  </color>
  <material>
   Вискоза
  </material>
  <price>
   337654
  </price>
  <rating>
   2.09
  </rating>
  <reviews>
   346535
  </reviews>
  <new>
   -
  </new>
  <exclusive>
   no
  </exclusive>
  <sporty>
   yes
  </sporty>
 </clothing>
 <clothing>
  <id>
   438637413
  </id>
  <name>
   Nike Pants L-7453
  </name>
  <category>
   Pants
  </category>
  <size>
   M
  </size>
  <color>
   Голубой
  </color>
  <material>
   Шелк
  </material>
  <price>
   893928
  </price>
  <rating>
   4.73
  </rating>
  <reviews>
   61983
  </reviews>
  <new>
   -
  </new>
  <exclusive>
   no
  </exclusive>
  <sporty>
   yes
  </sporty>
 </clothing>
 <clothing>
  <id>
   544086151
  </id>
  <name>
   New Balance Dress P-8085
  </name>
  <category>
   Dress
  </category>
  <size>
   L
  </size>
  <color>
   Красный
  </color>
  <material>
   Нейлон
  </material>
  <price>
   137739
  </price>
  <rating>
   1.79
  </rating>
  <reviews>
   141397
  </reviews>
  <new>
   +
  </new>
  <exclusive>
   no
  </exclusive>
 </clothing>
 <clothing>
  <id>
   300025371
  </id>
  <name>
   Addidas Jeans F-4173
  </name>
  <category>
   Jeans
  </category>
  <size>
   S
  </size>
  <color>
   Голубой
  </color>
  <material>
   Лен
  </material>
  <price>
   740216
  </price>
  <rating>
   3.28
  </rating>
  <reviews>
   540130
  </reviews>
  <new>
   -
  </new>
  <exclusive>
   yes
  </exclusive>
  <sporty>
   no
  </sporty>
 </clothing>
 <clothing>
  <id>
   628275263
  </id>
  <name>
   Adidas Umbrellas J-3488
  </name>
  <category>
   Umbrellas
  </category>
  <size>
   M
  </size>
  <color>
   Желтый
  </color>
  <material>
   Вискоза
  </material>
  <price>
   273783
  </price>
  <rating>
   3.63
  </rating>
  <reviews>
   439458
  </reviews>
  <exclusive>
   no
  </exclusive>
 </clothing>
 <clothing>
  <id>
   832462652
  </id>
  <name>
   Under Armour Blouse F-3581
  </name>
  <category>
   Blouse
  </category>
  <size>
   M
  </size>
  <color>
   Красный
  </color>
  <material>
   Полиэстер
  </material>
  <price>
   787753
  </price>
  <rating>
   1.09
  </rating>
  <reviews>
   953608
  </reviews>
 </clothing>
 <clothing>
  <id>
   988334304
  </id>
  <name>
   Ellesse Belts Q-5146
  </name>
  <category>
   Belts
  </category>
  <size>
   XXL
  </size>
  <color>
   Красный
  </color>
  <material>
   Шелк
  </material>
  <price>
   948239
  </price>
  <rating>
   3.18
  </rating>
  <reviews>
   246294
  </reviews>
  <new>
   -
  </new>
  <exclusive>
   no
  </exclusive>
  <sporty>
   no
  </sporty>
 </clothing>
 <clothing>
  <id>
   241333198
  </id>
  <name>
   Fila Hat P-9506
  </name>
  <category>
   Hat
  </category>
  <size>
   S
  </size>
  <color>
   Желтый
  </color>
  <material>
   Лен
  </material>
  <price>
   786092
  </price>
  <rating>
   2.3
  </rating>
  <reviews>
   99934
  </reviews>
  <exclusive>
   no
  </exclusive>
 </clothing>
 <clothing>
  <id>
   685703833
  </id>
  <name>
   DC Hat B-2007
  </name>
  <category>
   Hat
  </category>
  <size>
   M
  </size>
  <color>
   Зеленый
  </color>
  <material>
   Полиэстер
  </material>
  <price>
   693852
  </price>
  <rating>
   4.87
  </rating>
  <reviews>
   244120
  </reviews>
  <new>
   +
  </new>
  <exclusive>
   no
  </exclusive>
 </clothing>
 <clothing>
  <id>
   290579764
  </id>
  <name>
   Fila Jacket I-1860
  </name>
  <category>
   Jacket
  </category>
  <size>
   XXL
  </size>
  <color>
   Желтый
  </color>
  <material>
   Хлопок
  </material>
  <price>
   816145
  </price>
  <rating>
   2.29
  </rating>
  <reviews>
   359272
  </reviews>
  <new>
   +
  </new>
  <exclusive>
   yes
  </exclusive>
 </clothing>
 <clothing>
  <id>
   546493348
  </id>
  <name>
   Vans Pants Y-6426
  </name>
  <category>
   Pants
  </category>
  <size>
   L
  </size>
  <color>
   Зеленый
  </color>
  <material>
   Шерсть
  </material>
  <price>
   781117
  </price>
  <rating>
   2.8
  </rating>
  <reviews>
   954183
  </reviews>
  <new>
   -
  </new>
  <exclusive>
   yes
  </exclusive>
  <sporty>
   yes
  </sporty>
 </clothing>
 <clothing>
  <id>
   608640229
  </id>
  <name>
   Fila Gloves Z-3690
  </name>
  <category>
   Gloves
  </category>
  <size>
   M
  </size>
  <color>
   Желтый
  </color>
  <material>
   Шерсть
  </material>
  <price>
   665075
  </price>
  <rating>
   4.41
  </rating>
  <reviews>
   454956
  </reviews>
  <new>
   +
  </new>
 </clothing>
 <clothing>
  <id>
   268821315
  </id>
  <name>
   Lacoste Sweater T-8743
  </name>
  <category>
   Sweater
  </category>
  <size>
   S
  </size>
  <color>
   Голубой
  </color>
  <material>
   Вискоза
  </material>
  <price>
   748059
  </price>
  <rating>
   3.75
  </rating>
  <reviews>
   378204
  </reviews>
 </clothing>
 <clothing>
  <id>
   283491306
  </id>
  <name>
   Reebok Dress B-7285
  </name>
  <category>
   Dress
  </category>
  <size>
   S
  </size>
  <color>
   Красный
  </color>
  <material>
   Вискоза
  </material>
  <price>
   996536
  </price>
  <rating>
   3.4
  </rating>
  <reviews>
   273567
  </reviews>
  <new>
   -
  </new>
  <exclusive>
   yes
  </exclusive>
 </clothing>
 <clothing>
  <id>
   834880372
  </id>
  <name>
   Vans Dress J-8403
  </name>
  <category>
   Dress
  </category>
  <size>
   XL
  </size>
  <color>
   Желтый
  </color>
  <material>
   Хлопок
  </material>
  <price>
   811351
  </price>
  <rating>
   1.31
  </rating>
  <reviews>
   825629
  </reviews>
  <new>
   +
  </new>
  <exclusive>
   no
  </exclusive>
  <sporty>
   yes
  </sporty>
 </clothing>
 <clothing>
  <id>
   113400545
  </id>
  <name>
   Asics Skirt F-5515
  </name>
  <category>
   Skirt
  </category>
  <size>
   S
  </size>
  <color>
   Зеленый
  </color>
  <material>
   Лен
  </material>
  <price>
   604317
  </price>
  <rating>
   4.95
  </rating>
  <reviews>
   156157
  </reviews>
  <exclusive>
   yes
  </exclusive>
 </clothing>
 <clothing>
  <id>
   919076205
  </id>
  <name>
   Lacoste Jacket H-1415
  </name>
  <category>
   Jacket
  </category>
  <size>
   XXL
  </size>
  <color>
   Фиолетовый
  </color>
  <material>
   Шерсть
  </material>
  <price>
   379024
  </price>
  <rating>
   3.39
  </rating>
  <reviews>
   181851
  </reviews>
  <sporty>
   yes
  </sporty>
 </clothing>
 <clothing>
  <id>
   507707181
  </id>
  <name>
   Under Armour Handbags C-4545
  </name>
  <category>
   Handbags
  </category>
  <size>
   XXL
  </size>
  <color>
   Голубой
  </color>
  <material>
   Хлопок
  </material>
  <price>
   979922
  </price>
  <rating>
   3.9
  </rating>
  <reviews>
   468009
  </reviews>
  <exclusive>
   no
  </exclusive>
 </clothing>
 <clothing>
  <id>
   201743864
  </id>
  <name>
   Fila Jeans B-9652
  </name>
  <category>
   Jeans
  </category>
  <size>
   XL
  </size>
  <color>
   Желтый
  </color>
  <material>
   Вискоза
  </material>
  <price>
   600745
  </price>
  <rating>
   2.29
  </rating>
  <reviews>
   654964
  </reviews>
  <new>
   -
  </new>
  <sporty>
   no
  </sporty>
 </clothing>
 <clothing>
  <id>
   359882434
  </id>
  <name>
   Addidas Belts U-7166
  </name>
  <category>
   Belts
  </category>
  <size>
   XL
  </size>
  <color>
   Фиолетовый
  </color>
  <material>
   Хлопок
  </material>
  <price>
   866749
  </price>
  <rating>
   2.81
  </rating>
  <reviews>
   552664
  </reviews>
  <exclusive>
   no
  </exclusive>
  <sporty>
   no
  </sporty>
 </clothing>
 <clothing>
  <id>
   414071598
  </id>
  <name>
   Asics Blouse I-8400
  </name>
  <category>
   Blouse
  </category>
  <size>
   XL
  </size>
  <color>
   Зеленый
  </color>
  <material>
   Полиэстер
  </material>
  <price>
   541724
  </price>
  <rating>
   2.36
  </rating>
  <reviews>
   820353
  </reviews>
  <new>
   -
  </new>
  <sporty>
   yes
  </sporty>
 </clothing>
 <clothing>
  <id>
   262067261
  </id>
  <name>
   Converse Gloves R-1865
  </name>
  <category>
   Gloves
  </category>
  <size>
   XXL
  </size>
  <color>
   Зеленый
  </color>
  <material>
   Хлопок
  </material>
  <price>
   699273
  </price>
  <rating>
   3.71
  </rating>
  <reviews>
   558806
  </reviews>
  <sporty>
   yes
  </sporty>
 </clothing>
 <clothing>
  <id>
   420669943
  </id>
  <name>
   Under Armour Jeans O-8558
  </name>
  <category>
   Jeans
  </category>
  <size>
   XXL
  </size>
  <color>
   Голубой
  </color>
  <material>
   Нейлон
  </material>
  <price>
   636389
  </price>
  <rating>
   2.19
  </rating>
  <reviews>
   743027
  </reviews>
  <exclusive>
   no
  </exclusive>
 </clothing>
 <clothing>
  <id>
   870936651
  </id>
  <name>
   Adidas Umbrellas E-8011
  </name>
  <category>
   Umbrellas
  </category>
  <size>
   M
  </size>
  <color>
   Голубой
  </color>
  <material>
   Кожа
  </material>
  <price>
   266179
  </price>
  <rating>
   2.07
  </rating>
  <reviews>
   928565
  </reviews>
  <new>
   -
  </new>
  <exclusive>
   yes
  </exclusive>
 </clothing>
 <clothing>
  <id>
   662595811
  </id>
  <name>
   Brooks Belts M-3754
  </name>
  <category>
   Belts
  </category>
  <size>
   S
  </size>
  <color>
   Зеленый
  </color>
  <material>
   Вискоза
  </material>
  <price>
   801061
  </price>
  <rating>
   2.13
  </rating>
  <reviews>
   243076
  </reviews>
  <new>
   +
  </new>
  <exclusive>
   yes
  </exclusive>
  <sporty>
   no
  </sporty>
 </clothing>
 <clothing>
  <id>
   254492497
  </id>
  <name>
   Asics Belts B-3645
  </name>
  <category>
   Belts
  </category>
  <size>
   XXL
  </size>
  <color>
   Фиолетовый
  </color>
  <material>
   Вискоза
  </material>
  <price>
   104576
  </price>
  <rating>
   1.58
  </rating>
  <reviews>
   684731
  </reviews>
  <new>
   +
  </new>
  <sporty>
   no
  </sporty>
 </clothing>
 <clothing>
  <id>
   372451695
  </id>
  <name>
   PleinSport Blouse J-6411
  </name>
  <category>
   Blouse
  </category>
  <size>
   XL
  </size>
  <color>
   Красный
  </color>
  <material>
   Кожа
  </material>
  <price>
   308754
  </price>
  <rating>
   4.68
  </rating>
  <reviews>
   421811
  </reviews>
  <sporty>
   no
  </sporty>
 </clothing>
 <clothing>
  <id>
   787082092
  </id>
  <name>
   Nike Shirt I-4755
  </name>
  <category>
   Shirt
  </category>
  <size>
   M
  </size>
  <color>
   Зеленый
  </color>
  <material>
   Вискоза
  </material>
  <price>
   669446
  </price>
  <rating>
   4.17
  </rating>
  <reviews>
   185159
  </reviews>
  <new>
   -
  </new>
  <sporty>
   no
  </sporty>
 </clothing>
 <clothing>
  <id>
   461421917
  </id>
  <name>
   Nike Jeans B-9951
  </name>
  <category>
   Jeans
  </category>
  <size>
   XXL
  </size>
  <color>
   Голубой
  </color>
  <material>
   Нейлон
  </material>
  <price>
   425331
  </price>
  <rating>
   2.95
  </rating>
  <reviews>
   596529
  </reviews>
  <exclusive>
   yes
  </exclusive>
  <sporty>
   yes
  </sporty>
 </clothing>
 <clothing>
  <id>
   371753291
  </id>
  <name>
   Adidas Shirt W-9982
  </name>
  <category>
   Shirt
  </category>
  <size>
   XL
  </size>
  <color>
   Красный
  </color>
  <material>
   Шерсть
  </material>
  <price>
   398466
  </price>
  <rating>
   1.46
  </rating>
  <reviews>
   190360
  </reviews>
  <exclusive>
   no
  </exclusive>
 </clothing>
 <clothing>
  <id>
   282819479
  </id>
  <name>
   Ellesse Blouse V-4075
  </name>
  <category>
   Blouse
  </category>
  <size>
   XL
  </size>
  <color>
   Зеленый
  </color>
  <material>
   Полиэстер
  </material>
  <price>
   990588
  </price>
  <rating>
   1.17
  </rating>
  <reviews>
   117986
  </reviews>
  <new>
   +
  </new>
  <exclusive>
   no
  </exclusive>
 </clothing>
 <clothing>
  <id>
   641573182
  </id>
  <name>
   Lacoste Handbags D-4827
  </name>
  <category>
   Handbags
  </category>
  <size>
   M
  </size>
  <color>
   Зеленый
  </color>
  <material>
   Полиэстер
  </material>
  <price>
   442876
  </price>
  <rating>
   2.89
  </rating>
  <reviews>
   723360
  </reviews>
  <new>
   -
  </new>
  <exclusive>
   no
  </exclusive>
 </clothing>
 <clothing>
  <id>
   378143337
  </id>
  <name>
   Lacoste Shoes F-3667
  </name>
  <category>
   Shoes
  </category>
  <size>
   XXL
  </size>
  <color>
   Зеленый
  </color>
  <material>
   Шелк
  </material>
  <price>
   882872
  </price>
  <rating>
   4.23
  </rating>
  <reviews>
   582814
  </reviews>
  <sporty>
   no
  </sporty>
 </clothing>
 <clothing>
  <id>
   386506968
  </id>
  <name>
   Lacoste Jeans I-1441
  </name>
  <category>
   Jeans
  </category>
  <size>
   M
  </size>
  <color>
   Фиолетовый
  </color>
  <material>
   Лен
  </material>
  <price>
   172545
  </price>
  <rating>
   3.31
  </rating>
  <reviews>
   710214
  </reviews>
  <new>
   +
  </new>
  <exclusive>
   no
  </exclusive>
  <sporty>
   no
  </sporty>
 </clothing>
</clothing-items>
