<?xml version="1.0" encoding="utf-8"?>
<clothing-items>
 <clothing>
  <id>
   564116010
  </id>
  <name>
   Puma Pants O-3288
  </name>
  <category>
   Pants
  </category>
  <size>
   L
  </size>
  <color>
   Голубой
  </color>
  <material>
   Лен
  </material>
  <price>
   839973
  </price>
  <rating>
   1.71
  </rating>
  <reviews>
   854178
  </reviews>
  <exclusive>
   yes
  </exclusive>
  <sporty>
   no
  </sporty>
 </clothing>
 <clothing>
  <id>
   941729584
  </id>
  <name>
   Addidas Blouse J-5609
  </name>
  <category>
   Blouse
  </category>
  <size>
   L
  </size>
  <color>
   Голубой
  </color>
  <material>
   Шерсть
  </material>
  <price>
   822530
  </price>
  <rating>
   2.0
  </rating>
  <reviews>
   14714
  </reviews>
  <sporty>
   no
  </sporty>
 </clothing>
 <clothing>
  <id>
   891159580
  </id>
  <name>
   Addidas Dress F-3981
  </name>
  <category>
   Dress
  </category>
  <size>
   XXL
  </size>
  <color>
   Синий
  </color>
  <material>
   Вискоза
  </material>
  <price>
   693148
  </price>
  <rating>
   4.43
  </rating>
  <reviews>
   724282
  </reviews>
  <exclusive>
   yes
  </exclusive>
 </clothing>
 <clothing>
  <id>
   394217646
  </id>
  <name>
   Reebok Dress V-4723
  </name>
  <category>
   Dress
  </category>
  <size>
   XXL
  </size>
  <color>
   Желтый
  </color>
  <material>
   Кожа
  </material>
  <price>
   407075
  </price>
  <rating>
   2.21
  </rating>
  <reviews>
   737461
  </reviews>
  <new>
   -
  </new>
  <sporty>
   no
  </sporty>
 </clothing>
 <clothing>
  <id>
   824193980
  </id>
  <name>
   Under Armour T-shirt M-5464
  </name>
  <category>
   T-shirt
  </category>
  <size>
   L
  </size>
  <color>
   Зеленый
  </color>
  <material>
   Вискоза
  </material>
  <price>
   939294
  </price>
  <rating>
   1.86
  </rating>
  <reviews>
   385336
  </reviews>
  <exclusive>
   no
  </exclusive>
 </clothing>
 <clothing>
  <id>
   339242292
  </id>
  <name>
   Puma Sweater O-5405
  </name>
  <category>
   Sweater
  </category>
  <size>
   L
  </size>
  <color>
   Фиолетовый
  </color>
  <material>
   Кожа
  </material>
  <price>
   108688
  </price>
  <rating>
   3.54
  </rating>
  <reviews>
   605035
  </reviews>
  <new>
   -
  </new>
  <sporty>
   no
  </sporty>
 </clothing>
 <clothing>
  <id>
   439801265
  </id>
  <name>
   Addidas Hat I-5576
  </name>
  <category>
   Hat
  </category>
  <size>
   XXL
  </size>
  <color>
   Синий
  </color>
  <material>
   Лен
  </material>
  <price>
   929702
  </price>
  <rating>
   2.07
  </rating>
  <reviews>
   420471
  </reviews>
  <new>
   -
  </new>
 </clothing>
 <clothing>
  <id>
   824504484
  </id>
  <name>
   Ellesse Socks V-2481
  </name>
  <category>
   Socks
  </category>
  <size>
   M
  </size>
  <color>
   Желтый
  </color>
  <material>
   Вискоза
  </material>
  <price>
   829231
  </price>
  <rating>
   3.14
  </rating>
  <reviews>
   553175
  </reviews>
  <new>
   +
  </new>
  <sporty>
   yes
  </sporty>
 </clothing>
 <clothing>
  <id>
   678993563
  </id>
  <name>
   PleinSport Handbags T-8546
  </name>
  <category>
   Handbags
  </category>
  <size>
   XXL
  </size>
  <color>
   Голубой
  </color>
  <material>
   Хлопок
  </material>
  <price>
   480907
  </price>
  <rating>
   3.85
  </rating>
  <reviews>
   750776
  </reviews>
  <new>
   +
  </new>
  <exclusive>
   no
  </exclusive>
 </clothing>
 <clothing>
  <id>
   955188431
  </id>
  <name>
   DC Pants D-9896
  </name>
  <category>
   Pants
  </category>
  <size>
   M
  </size>
  <color>
   Фиолетовый
  </color>
  <material>
   Лен
  </material>
  <price>
   692287
  </price>
  <rating>
   2.91
  </rating>
  <reviews>
   827143
  </reviews>
  <new>
   +
  </new>
  <exclusive>
   no
  </exclusive>
  <sporty>
   no
  </sporty>
 </clothing>
 <clothing>
  <id>
   224666825
  </id>
  <name>
   Brooks Blouse R-1570
  </name>
  <category>
   Blouse
  </category>
  <size>
   XXL
  </size>
  <color>
   Желтый
  </color>
  <material>
   Шелк
  </material>
  <price>
   748938
  </price>
  <rating>
   4.27
  </rating>
  <reviews>
   566978
  </reviews>
  <new>
   -
  </new>
  <exclusive>
   no
  </exclusive>
  <sporty>
   no
  </sporty>
 </clothing>
 <clothing>
  <id>
   197245877
  </id>
  <name>
   DC Sweater K-8189
  </name>
  <category>
   Sweater
  </category>
  <size>
   M
  </size>
  <color>
   Фиолетовый
  </color>
  <material>
   Нейлон
  </material>
  <price>
   940202
  </price>
  <rating>
   1.97
  </rating>
  <reviews>
   734726
  </reviews>
  <new>
   +
  </new>
  <sporty>
   yes
  </sporty>
 </clothing>
 <clothing>
  <id>
   369952642
  </id>
  <name>
   Fila Gloves D-9274
  </name>
  <category>
   Gloves
  </category>
  <size>
   L
  </size>
  <color>
   Желтый
  </color>
  <material>
   Вискоза
  </material>
  <price>
   405126
  </price>
  <rating>
   1.11
  </rating>
  <reviews>
   826292
  </reviews>
  <new>
   +
  </new>
  <exclusive>
   yes
  </exclusive>
  <sporty>
   no
  </sporty>
 </clothing>
 <clothing>
  <id>
   391714309
  </id>
  <name>
   Lacoste Jacket B-9274
  </name>
  <category>
   Jacket
  </category>
  <size>
   XL
  </size>
  <color>
   Фиолетовый
  </color>
  <material>
   Шелк
  </material>
  <price>
   493775
  </price>
  <rating>
   1.63
  </rating>
  <reviews>
   491479
  </reviews>
  <new>
   -
  </new>
 </clothing>
 <clothing>
  <id>
   321342854
  </id>
  <name>
   Fila Hat L-1622
  </name>
  <category>
   Hat
  </category>
  <size>
   M
  </size>
  <color>
   Красный
  </color>
  <material>
   Шерсть
  </material>
  <price>
   736594
  </price>
  <rating>
   3.55
  </rating>
  <reviews>
   132124
  </reviews>
  <new>
   -
  </new>
  <exclusive>
   yes
  </exclusive>
  <sporty>
   yes
  </sporty>
 </clothing>
 <clothing>
  <id>
   591401418
  </id>
  <name>
   Ellesse Blouse K-5364
  </name>
  <category>
   Blouse
  </category>
  <size>
   M
  </size>
  <color>
   Оранжевый
  </color>
  <material>
   Шерсть
  </material>
  <price>
   125144
  </price>
  <rating>
   3.24
  </rating>
  <reviews>
   565461
  </reviews>
  <exclusive>
   yes
  </exclusive>
  <sporty>
   no
  </sporty>
 </clothing>
 <clothing>
  <id>
   924505625
  </id>
  <name>
   Asics Handbags D-9153
  </name>
  <category>
   Handbags
  </category>
  <size>
   M
  </size>
  <color>
   Красный
  </color>
  <material>
   Шелк
  </material>
  <price>
   880681
  </price>
  <rating>
   1.17
  </rating>
  <reviews>
   584761
  </reviews>
  <new>
   -
  </new>
  <exclusive>
   yes
  </exclusive>
 </clothing>
 <clothing>
  <id>
   137610324
  </id>
  <name>
   New Balance Blouse N-7962
  </name>
  <category>
   Blouse
  </category>
  <size>
   M
  </size>
  <color>
   Голубой
  </color>
  <material>
   Вискоза
  </material>
  <price>
   216760
  </price>
  <rating>
   4.37
  </rating>
  <reviews>
   761263
  </reviews>
  <new>
   -
  </new>
  <exclusive>
   yes
  </exclusive>
  <sporty>
   yes
  </sporty>
 </clothing>
 <clothing>
  <id>
   558882937
  </id>
  <name>
   Lacoste Dress E-5120
  </name>
  <category>
   Dress
  </category>
  <size>
   XXL
  </size>
  <color>
   Желтый
  </color>
  <material>
   Полиэстер
  </material>
  <price>
   563372
  </price>
  <rating>
   1.02
  </rating>
  <reviews>
   4480
  </reviews>
  <new>
   -
  </new>
 </clothing>
 <clothing>
  <id>
   603951279
  </id>
  <name>
   Lacoste Gloves W-1425
  </name>
  <category>
   Gloves
  </category>
  <size>
   L
  </size>
  <color>
   Фиолетовый
  </color>
  <material>
   Вискоза
  </material>
  <price>
   291364
  </price>
  <rating>
   3.2
  </rating>
  <reviews>
   845368
  </reviews>
  <new>
   -
  </new>
 </clothing>
 <clothing>
  <id>
   953637897
  </id>
  <name>
   Asics Handbags L-1622
  </name>
  <category>
   Handbags
  </category>
  <size>
   S
  </size>
  <color>
   Синий
  </color>
  <material>
   Хлопок
  </material>
  <price>
   741239
  </price>
  <rating>
   5.0
  </rating>
  <reviews>
   569851
  </reviews>
  <new>
   -
  </new>
  <exclusive>
   yes
  </exclusive>
  <sporty>
   no
  </sporty>
 </clothing>
</clothing-items>
