<?xml version="1.0" encoding="utf-8"?>
<clothing-items>
 <clothing>
  <id>
   784720687
  </id>
  <name>
   Puma Umbrellas I-3018
  </name>
  <category>
   Umbrellas
  </category>
  <size>
   S
  </size>
  <color>
   Голубой
  </color>
  <material>
   Хлопок
  </material>
  <price>
   881229
  </price>
  <rating>
   1.51
  </rating>
  <reviews>
   245476
  </reviews>
  <sporty>
   no
  </sporty>
 </clothing>
 <clothing>
  <id>
   433076652
  </id>
  <name>
   Under Armour Handbags U-1807
  </name>
  <category>
   Handbags
  </category>
  <size>
   L
  </size>
  <color>
   Голубой
  </color>
  <material>
   Кожа
  </material>
  <price>
   429996
  </price>
  <rating>
   2.28
  </rating>
  <reviews>
   500480
  </reviews>
  <sporty>
   yes
  </sporty>
 </clothing>
 <clothing>
  <id>
   738565049
  </id>
  <name>
   Under Armour Belts W-5794
  </name>
  <category>
   Belts
  </category>
  <size>
   M
  </size>
  <color>
   Фиолетовый
  </color>
  <material>
   Кожа
  </material>
  <price>
   574237
  </price>
  <rating>
   3.75
  </rating>
  <reviews>
   627626
  </reviews>
  <new>
   -
  </new>
  <sporty>
   yes
  </sporty>
 </clothing>
 <clothing>
  <id>
   434385463
  </id>
  <name>
   Under Armour Jeans E-7322
  </name>
  <category>
   Jeans
  </category>
  <size>
   XL
  </size>
  <color>
   Желтый
  </color>
  <material>
   Шелк
  </material>
  <price>
   521560
  </price>
  <rating>
   1.89
  </rating>
  <reviews>
   753641
  </reviews>
  <new>
   -
  </new>
  <exclusive>
   yes
  </exclusive>
 </clothing>
 <clothing>
  <id>
   441415486
  </id>
  <name>
   Lacoste Shirt L-1133
  </name>
  <category>
   Shirt
  </category>
  <size>
   L
  </size>
  <color>
   Синий
  </color>
  <material>
   Полиэстер
  </material>
  <price>
   244558
  </price>
  <rating>
   4.17
  </rating>
  <reviews>
   16352
  </reviews>
  <exclusive>
   yes
  </exclusive>
 </clothing>
 <clothing>
  <id>
   279296587
  </id>
  <name>
   Adidas Skirt D-2342
  </name>
  <category>
   Skirt
  </category>
  <size>
   M
  </size>
  <color>
   Желтый
  </color>
  <material>
   Полиэстер
  </material>
  <price>
   237975
  </price>
  <rating>
   2.46
  </rating>
  <reviews>
   78065
  </reviews>
  <new>
   -
  </new>
  <exclusive>
   no
  </exclusive>
 </clothing>
 <clothing>
  <id>
   861524591
  </id>
  <name>
   Vans Gloves M-2046
  </name>
  <category>
   Gloves
  </category>
  <size>
   XL
  </size>
  <color>
   Синий
  </color>
  <material>
   Лен
  </material>
  <price>
   110409
  </price>
  <rating>
   2.55
  </rating>
  <reviews>
   210613
  </reviews>
  <new>
   -
  </new>
 </clothing>
 <clothing>
  <id>
   549807698
  </id>
  <name>
   Fila Shoes Z-6537
  </name>
  <category>
   Shoes
  </category>
  <size>
   M
  </size>
  <color>
   Красный
  </color>
  <material>
   Шерсть
  </material>
  <price>
   757128
  </price>
  <rating>
   3.13
  </rating>
  <reviews>
   420301
  </reviews>
  <sporty>
   yes
  </sporty>
 </clothing>
 <clothing>
  <id>
   375280748
  </id>
  <name>
   Adidas Blouse R-8954
  </name>
  <category>
   Blouse
  </category>
  <size>
   L
  </size>
  <color>
   Желтый
  </color>
  <material>
   Лен
  </material>
  <price>
   313487
  </price>
  <rating>
   4.04
  </rating>
  <reviews>
   317784
  </reviews>
  <sporty>
   no
  </sporty>
 </clothing>
 <clothing>
  <id>
   263157554
  </id>
  <name>
   PleinSport Jeans F-8371
  </name>
  <category>
   Jeans
  </category>
  <size>
   M
  </size>
  <color>
   Оранжевый
  </color>
  <material>
   Хлопок
  </material>
  <price>
   747026
  </price>
  <rating>
   1.72
  </rating>
  <reviews>
   64939
  </reviews>
  <exclusive>
   yes
  </exclusive>
  <sporty>
   no
  </sporty>
 </clothing>
 <clothing>
  <id>
   362977969
  </id>
  <name>
   Fila T-shirt V-7327
  </name>
  <category>
   T-shirt
  </category>
  <size>
   XXL
  </size>
  <color>
   Оранжевый
  </color>
  <material>
   Вискоза
  </material>
  <price>
   766671
  </price>
  <rating>
   4.93
  </rating>
  <reviews>
   336475
  </reviews>
  <new>
   +
  </new>
  <exclusive>
   no
  </exclusive>
 </clothing>
 <clothing>
  <id>
   890135087
  </id>
  <name>
   Converse Jeans J-5130
  </name>
  <category>
   Jeans
  </category>
  <size>
   L
  </size>
  <color>
   Зеленый
  </color>
  <material>
   Полиэстер
  </material>
  <price>
   560595
  </price>
  <rating>
   4.41
  </rating>
  <reviews>
   34292
  </reviews>
  <sporty>
   yes
  </sporty>
 </clothing>
 <clothing>
  <id>
   148545753
  </id>
  <name>
   Reebok Dress R-4689
  </name>
  <category>
   Dress
  </category>
  <size>
   XL
  </size>
  <color>
   Оранжевый
  </color>
  <material>
   Лен
  </material>
  <price>
   627538
  </price>
  <rating>
   1.92
  </rating>
  <reviews>
   724374
  </reviews>
  <exclusive>
   yes
  </exclusive>
 </clothing>
</clothing-items>
