<?xml version="1.0" encoding="utf-8"?>
<clothing-items>
 <clothing>
  <id>
   807423787
  </id>
  <name>
   Addidas Shirt F-7655
  </name>
  <category>
   Shirt
  </category>
  <size>
   S
  </size>
  <color>
   Синий
  </color>
  <material>
   Кожа
  </material>
  <price>
   476364
  </price>
  <rating>
   1.58
  </rating>
  <reviews>
   571418
  </reviews>
 </clothing>
 <clothing>
  <id>
   759881769
  </id>
  <name>
   New Balance Dress U-3747
  </name>
  <category>
   Dress
  </category>
  <size>
   XL
  </size>
  <color>
   Желтый
  </color>
  <material>
   Шелк
  </material>
  <price>
   202155
  </price>
  <rating>
   3.4
  </rating>
  <reviews>
   419955
  </reviews>
  <new>
   -
  </new>
  <exclusive>
   no
  </exclusive>
  <sporty>
   yes
  </sporty>
 </clothing>
 <clothing>
  <id>
   104163870
  </id>
  <name>
   Brooks Umbrellas L-8720
  </name>
  <category>
   Umbrellas
  </category>
  <size>
   S
  </size>
  <color>
   Оранжевый
  </color>
  <material>
   Шелк
  </material>
  <price>
   463591
  </price>
  <rating>
   1.84
  </rating>
  <reviews>
   290257
  </reviews>
  <new>
   -
  </new>
  <exclusive>
   yes
  </exclusive>
  <sporty>
   no
  </sporty>
 </clothing>
 <clothing>
  <id>
   876895453
  </id>
  <name>
   Converse Umbrellas Y-6437
  </name>
  <category>
   Umbrellas
  </category>
  <size>
   XL
  </size>
  <color>
   Синий
  </color>
  <material>
   Полиэстер
  </material>
  <price>
   690083
  </price>
  <rating>
   4.91
  </rating>
  <reviews>
   432554
  </reviews>
  <sporty>
   no
  </sporty>
 </clothing>
 <clothing>
  <id>
   880612269
  </id>
  <name>
   Lacoste Shoes Q-1941
  </name>
  <category>
   Shoes
  </category>
  <size>
   XXL
  </size>
  <color>
   Синий
  </color>
  <material>
   Шерсть
  </material>
  <price>
   872809
  </price>
  <rating>
   1.34
  </rating>
  <reviews>
   957594
  </reviews>
  <new>
   -
  </new>
  <exclusive>
   yes
  </exclusive>
 </clothing>
 <clothing>
  <id>
   927308294
  </id>
  <name>
   Vans Sweater Y-6982
  </name>
  <category>
   Sweater
  </category>
  <size>
   M
  </size>
  <color>
   Зеленый
  </color>
  <material>
   Лен
  </material>
  <price>
   219655
  </price>
  <rating>
   3.36
  </rating>
  <reviews>
   9294
  </reviews>
  <new>
   +
  </new>
  <sporty>
   no
  </sporty>
 </clothing>
 <clothing>
  <id>
   947601837
  </id>
  <name>
   Lacoste Dress O-3001
  </name>
  <category>
   Dress
  </category>
  <size>
   XXL
  </size>
  <color>
   Зеленый
  </color>
  <material>
   Шелк
  </material>
  <price>
   294914
  </price>
  <rating>
   3.32
  </rating>
  <reviews>
   58461
  </reviews>
  <new>
   +
  </new>
  <exclusive>
   no
  </exclusive>
 </clothing>
 <clothing>
  <id>
   669151501
  </id>
  <name>
   Puma Skirt R-4794
  </name>
  <category>
   Skirt
  </category>
  <size>
   XXL
  </size>
  <color>
   Голубой
  </color>
  <material>
   Хлопок
  </material>
  <price>
   569359
  </price>
  <rating>
   4.7
  </rating>
  <reviews>
   398793
  </reviews>
  <new>
   -
  </new>
  <exclusive>
   no
  </exclusive>
  <sporty>
   yes
  </sporty>
 </clothing>
 <clothing>
  <id>
   834975104
  </id>
  <name>
   New Balance Shoes Q-1738
  </name>
  <category>
   Shoes
  </category>
  <size>
   S
  </size>
  <color>
   Голубой
  </color>
  <material>
   Хлопок
  </material>
  <price>
   127548
  </price>
  <rating>
   4.86
  </rating>
  <reviews>
   335395
  </reviews>
  <sporty>
   no
  </sporty>
 </clothing>
 <clothing>
  <id>
   706438427
  </id>
  <name>
   Ellesse T-shirt G-5962
  </name>
  <category>
   T-shirt
  </category>
  <size>
   XL
  </size>
  <color>
   Зеленый
  </color>
  <material>
   Хлопок
  </material>
  <price>
   397349
  </price>
  <rating>
   3.18
  </rating>
  <reviews>
   642117
  </reviews>
  <new>
   -
  </new>
  <sporty>
   no
  </sporty>
 </clothing>
 <clothing>
  <id>
   674882919
  </id>
  <name>
   Converse Handbags J-7363
  </name>
  <category>
   Handbags
  </category>
  <size>
   L
  </size>
  <color>
   Фиолетовый
  </color>
  <material>
   Полиэстер
  </material>
  <price>
   698727
  </price>
  <rating>
   4.08
  </rating>
  <reviews>
   84826
  </reviews>
  <exclusive>
   yes
  </exclusive>
  <sporty>
   yes
  </sporty>
 </clothing>
 <clothing>
  <id>
   489189617
  </id>
  <name>
   Brooks Shoes F-4474
  </name>
  <category>
   Shoes
  </category>
  <size>
   L
  </size>
  <color>
   Красный
  </color>
  <material>
   Шерсть
  </material>
  <price>
   893361
  </price>
  <rating>
   3.17
  </rating>
  <reviews>
   844761
  </reviews>
  <new>
   -
  </new>
 </clothing>
 <clothing>
  <id>
   778744698
  </id>
  <name>
   Puma Jacket V-5709
  </name>
  <category>
   Jacket
  </category>
  <size>
   S
  </size>
  <color>
   Фиолетовый
  </color>
  <material>
   Лен
  </material>
  <price>
   569877
  </price>
  <rating>
   1.12
  </rating>
  <reviews>
   993882
  </reviews>
  <new>
   -
  </new>
  <exclusive>
   no
  </exclusive>
 </clothing>
 <clothing>
  <id>
   956748863
  </id>
  <name>
   Asics Shirt L-5259
  </name>
  <category>
   Shirt
  </category>
  <size>
   XXL
  </size>
  <color>
   Зеленый
  </color>
  <material>
   Хлопок
  </material>
  <price>
   107462
  </price>
  <rating>
   3.57
  </rating>
  <reviews>
   680973
  </reviews>
  <new>
   -
  </new>
  <exclusive>
   yes
  </exclusive>
  <sporty>
   yes
  </sporty>
 </clothing>
 <clothing>
  <id>
   188039641
  </id>
  <name>
   Under Armour T-shirt K-6342
  </name>
  <category>
   T-shirt
  </category>
  <size>
   L
  </size>
  <color>
   Желтый
  </color>
  <material>
   Вискоза
  </material>
  <price>
   104214
  </price>
  <rating>
   4.44
  </rating>
  <reviews>
   925786
  </reviews>
  <exclusive>
   no
  </exclusive>
  <sporty>
   yes
  </sporty>
 </clothing>
 <clothing>
  <id>
   792834471
  </id>
  <name>
   Brooks Gloves B-6322
  </name>
  <category>
   Gloves
  </category>
  <size>
   M
  </size>
  <color>
   Фиолетовый
  </color>
  <material>
   Хлопок
  </material>
  <price>
   676246
  </price>
  <rating>
   3.34
  </rating>
  <reviews>
   214073
  </reviews>
  <new>
   -
  </new>
  <exclusive>
   yes
  </exclusive>
  <sporty>
   yes
  </sporty>
 </clothing>
 <clothing>
  <id>
   188247675
  </id>
  <name>
   Lacoste Belts E-7145
  </name>
  <category>
   Belts
  </category>
  <size>
   M
  </size>
  <color>
   Зеленый
  </color>
  <material>
   Полиэстер
  </material>
  <price>
   568667
  </price>
  <rating>
   1.52
  </rating>
  <reviews>
   593514
  </reviews>
  <new>
   -
  </new>
  <exclusive>
   no
  </exclusive>
 </clothing>
 <clothing>
  <id>
   169353831
  </id>
  <name>
   Nike Belts Y-9981
  </name>
  <category>
   Belts
  </category>
  <size>
   XXL
  </size>
  <color>
   Зеленый
  </color>
  <material>
   Полиэстер
  </material>
  <price>
   262522
  </price>
  <rating>
   1.99
  </rating>
  <reviews>
   848484
  </reviews>
  <new>
   -
  </new>
  <sporty>
   yes
  </sporty>
 </clothing>
 <clothing>
  <id>
   913937802
  </id>
  <name>
   Lacoste Handbags H-1802
  </name>
  <category>
   Handbags
  </category>
  <size>
   S
  </size>
  <color>
   Красный
  </color>
  <material>
   Шерсть
  </material>
  <price>
   334491
  </price>
  <rating>
   4.69
  </rating>
  <reviews>
   231604
  </reviews>
  <sporty>
   no
  </sporty>
 </clothing>
 <clothing>
  <id>
   877949560
  </id>
  <name>
   Ellesse Belts W-5387
  </name>
  <category>
   Belts
  </category>
  <size>
   M
  </size>
  <color>
   Синий
  </color>
  <material>
   Шелк
  </material>
  <price>
   933710
  </price>
  <rating>
   4.74
  </rating>
  <reviews>
   933431
  </reviews>
  <new>
   -
  </new>
  <sporty>
   yes
  </sporty>
 </clothing>
 <clothing>
  <id>
   963787525
  </id>
  <name>
   New Balance Shoes G-4258
  </name>
  <category>
   Shoes
  </category>
  <size>
   XXL
  </size>
  <color>
   Фиолетовый
  </color>
  <material>
   Нейлон
  </material>
  <price>
   804328
  </price>
  <rating>
   4.49
  </rating>
  <reviews>
   38818
  </reviews>
  <new>
   -
  </new>
 </clothing>
 <clothing>
  <id>
   524624089
  </id>
  <name>
   New Balance Belts N-6398
  </name>
  <category>
   Belts
  </category>
  <size>
   XXL
  </size>
  <color>
   Оранжевый
  </color>
  <material>
   Нейлон
  </material>
  <price>
   611818
  </price>
  <rating>
   1.8
  </rating>
  <reviews>
   110071
  </reviews>
  <exclusive>
   yes
  </exclusive>
  <sporty>
   no
  </sporty>
 </clothing>
 <clothing>
  <id>
   163352696
  </id>
  <name>
   Vans Shoes S-9096
  </name>
  <category>
   Shoes
  </category>
  <size>
   M
  </size>
  <color>
   Голубой
  </color>
  <material>
   Шелк
  </material>
  <price>
   115427
  </price>
  <rating>
   4.39
  </rating>
  <reviews>
   966065
  </reviews>
  <new>
   +
  </new>
  <exclusive>
   no
  </exclusive>
 </clothing>
 <clothing>
  <id>
   144938459
  </id>
  <name>
   Brooks Umbrellas B-9157
  </name>
  <category>
   Umbrellas
  </category>
  <size>
   XXL
  </size>
  <color>
   Синий
  </color>
  <material>
   Шелк
  </material>
  <price>
   659661
  </price>
  <rating>
   3.87
  </rating>
  <reviews>
   420550
  </reviews>
  <new>
   -
  </new>
 </clothing>
 <clothing>
  <id>
   600178088
  </id>
  <name>
   Converse Jacket Y-4064
  </name>
  <category>
   Jacket
  </category>
  <size>
   L
  </size>
  <color>
   Оранжевый
  </color>
  <material>
   Нейлон
  </material>
  <price>
   835378
  </price>
  <rating>
   4.91
  </rating>
  <reviews>
   324384
  </reviews>
  <new>
   +
  </new>
  <sporty>
   no
  </sporty>
 </clothing>
 <clothing>
  <id>
   274153699
  </id>
  <name>
   Addidas Blouse T-6230
  </name>
  <category>
   Blouse
  </category>
  <size>
   L
  </size>
  <color>
   Синий
  </color>
  <material>
   Нейлон
  </material>
  <price>
   394993
  </price>
  <rating>
   1.34
  </rating>
  <reviews>
   74424
  </reviews>
  <new>
   -
  </new>
  <exclusive>
   no
  </exclusive>
  <sporty>
   no
  </sporty>
 </clothing>
</clothing-items>
