[{"id": 499761, "name": "Мемориал Таля 1967", "city": "Льейда", "begin": "16.10", "system": "circular", "tours_count": 12, "min_rating": 2650, "time_on_game": 158}, {"id": 845672, "name": "Европа 1984", "city": "Алма-Ата", "begin": "17.10", "system": "Olympic", "tours_count": 7, "min_rating": 2650, "time_on_game": 140}, {"id": 741417, "name": "Турнир претендентов 1980", "city": "Кадакес", "begin": "04.03", "system": "Olympic", "tours_count": 7, "min_rating": 2633, "time_on_game": 149}, {"id": 613225, "name": "Политика 2004", "city": "Баку", "begin": "04.04", "system": "Olympic", "tours_count": 14, "min_rating": 2625, "time_on_game": 68}, {"id": 287780, "name": "Мемориал Таля 1969", "city": "Вильявисиоса", "begin": "18.06", "system": "Swiss", "tours_count": 11, "min_rating": 2624, "time_on_game": 76}, {"id": 735771, "name": "Вейк-ан-Зее 1983", "city": "Белград", "begin": "14.07", "system": "Swiss", "tours_count": 14, "min_rating": 2621, "time_on_game": 125}, {"id": 318038, "name": "Цюрих 2007", "city": "Куэнка", "begin": "21.03", "system": "circular", "tours_count": 6, "min_rating": 2611, "time_on_game": 52}, {"id": 822086, "name": "Алушта 1997", "city": "Мартоса", "begin": "24.06", "system": "circular", "tours_count": 15, "min_rating": 2602, "time_on_game": 34}, {"id": 232078, "name": "Линарес 1971", "city": "Хихон", "begin": "18.05", "system": "Olympic", "tours_count": 9, "min_rating": 2601, "time_on_game": 25}, {"id": 252452, "name": "Sinquefield Cup 1959", "city": "Севилья", "begin": "08.12", "system": "Swiss", "tours_count": 10, "min_rating": 2588, "time_on_game": 140}, {"id": 738530, "name": "Вена 2012", "city": "Любляна", "begin": "27.08", "system": "circular", "tours_count": 9, "min_rating": 2587, "time_on_game": 150}, {"id": 104755, "name": "Чемпионат мира 1953", "city": "Минск", "begin": "27.10", "system": "Swiss", "tours_count": 12, "min_rating": 2577, "time_on_game": 101}, {"id": 640056, "name": "Реджо-нель-Эмилия 2023", "city": "Ереван", "begin": "12.05", "system": "Swiss", "tours_count": 11, "min_rating": 2569, "time_on_game": 25}, {"id": 542894, "name": "Ставангер 1951", "city": "Осера", "begin": "17.04", "system": "circular", "tours_count": 11, "min_rating": 2567, "time_on_game": 19}, {"id": 725339, "name": "Политика 1994", "city": "Трухильо", "begin": "04.08", "system": "circular", "tours_count": 6, "min_rating": 2544, "time_on_game": 56}, {"id": 683270, "name": "Вейк-ан-Зее 2008", "city": "Овьедо", "begin": "07.12", "system": "Olympic", "tours_count": 15, "min_rating": 2542, "time_on_game": 80}, {"id": 261538, "name": "Реджо-нель-Эмилия 2000", "city": "Сьюдад-Реаль", "begin": "23.03", "system": "Olympic", "tours_count": 14, "min_rating": 2536, "time_on_game": 178}, {"id": 417975, "name": "Сент-Луис 2008", "city": "Овьедо", "begin": "22.10", "system": "circular", "tours_count": 9, "min_rating": 2532, "time_on_game": 46}, {"id": 633967, "name": "Алушта 1999", "city": "Сьюдад-Реаль", "begin": "02.06", "system": "Olympic", "tours_count": 10, "min_rating": 2530, "time_on_game": 101}]